clusterfusion/__init__.py
clusterfusion/_clusterfusion.cpython-312-x86_64-linux-gnu.so
clusterfusion-0.0.0.dist-info/METADATA
clusterfusion-0.0.0.dist-info/WHEEL
clusterfusion-0.0.0.dist-info/top_level.txt
clusterfusion-0.0.0.dist-info/RECORD
