Metadata-Version: 2.4
Name: clusterfusion
Version: 0.0.0
Classifier: Development Status :: 3 - Alpha
Classifier: Intended Audience :: Science/Research
Classifier: Topic :: Scientific/Engineering :: Artificial Intelligence
Classifier: Programming Language :: Python :: 3.12
Requires-Dist: torch
Dynamic: classifier
Dynamic: requires-dist
